aspace/__init__.py
aspace/_version.py
aspace/base_client.py
aspace/client.py
aspace/constants.py
aspace/enums.py
aspace/jsonmodel.py
aspace/util.py
aspace/client_extensions/__init__.py
aspace/client_extensions/enum_management.py
aspace/client_extensions/jobs.py
aspace/client_extensions/record_streams.py
aspace/client_extensions/schema_query.py
aspace/client_extensions/top_containers.py
aspace/client_extensions/user_management.py
aspace_client-2.5.0.dist-info/LICENSE
aspace_client-2.5.0.dist-info/METADATA
aspace_client-2.5.0.dist-info/WHEEL
aspace_client-2.5.0.dist-info/top_level.txt
aspace_client-2.5.0.dist-info/RECORD
