Metadata-Version: 2.1
Name: aspace-client
Version: 2.5.0
Summary: Provides methods and classes that can be used when interacting with the ArchivesSpace API.
Home-page: https://github.com/AtlasSystems/ArchivesSpace-Python-Client
Author: Devgineers @ Atlas Systems Inc.
Author-email: devgineers@atlas-sys.com
License: UNKNOWN
Project-URL: Bug Reports, https://github.com/AtlasSystems/ArchivesSpace-Python-Client/issues
Project-URL: Feature Requests, https://github.com/AtlasSystems/ArchivesSpace-Python-Client/issues
Project-URL: Source, https://github.com/AtlasSystems/ArchivesSpace-Python-Client
Keywords: archivesspace archives api
Platform: UNKNOWN
Classifier: Development Status :: 5 - Production/Stable
Classifier: Intended Audience :: Developers
Classifier: Intended Audience :: System Administrators
Classifier: License :: OSI Approved :: MIT License
Classifier: Operating System :: OS Independent
Classifier: Programming Language :: Python :: 3
Classifier: Programming Language :: Python :: 3.3
Classifier: Programming Language :: Python :: 3.4
Classifier: Programming Language :: Python :: 3.5
Classifier: Programming Language :: Python :: 3.6
Classifier: Programming Language :: Python :: 3.7
Requires-Dist: requests (<3,>=2.18)
